[
  {
    "name": "Canva Designer",
    "source": "Unstop",
    "source_url": "https://unstop.com/undefined",
    "start_date": "2024-11-01T00:00:00+05:30",
    "end_date": "2025-02-01T23:59:59+05:30",
    "location": "",
    "college": ""
  },
  {
    "name": "Social Media Marketing",
    "source": "Unstop",
    "source_url": "https://unstop.com/undefined",
    "start_date": "2023-02-27T00:00:00+05:30",
    "end_date": "2023-03-03T00:00:00+05:30",
    "location": "",
    "college": ""
  },
  {
    "name": "Hands on training on x ray diffractometer",
    "source": "Unstop",
    "source_url": "https://unstop.com/undefined",
    "start_date": "2024-08-27T00:00:00+05:30",
    "end_date": "2024-09-12T00:00:00+05:30",
    "location": "",
    "college": ""
  },
  {
    "name": "Office Services Analyst",
    "source": "Unstop",
    "source_url": "https://unstop.com/undefined",
    "start_date": "2026-04-18T00:00:00+05:30",
    "end_date": "2026-05-02T00:00:00+05:30",
    "location": "",
    "college": ""
  },
  {
    "name": "B2B Sales Internship",
    "source": "Unstop",
    "source_url": "https://unstop.com/undefined",
    "start_date": "2026-04-18T00:00:00+05:30",
    "end_date": "2026-05-02T00:00:00+05:30",
    "location": "",
    "college": ""
  },
  {
    "name": "PAS EMS Tax Analyst-Switzerland",
    "source": "Unstop",
    "source_url": "https://unstop.com/undefined",
    "start_date": "2026-04-19T00:00:00+05:30",
    "end_date": "2026-05-03T00:00:00+05:30",
    "location": "",
    "college": ""
  },
  {
    "name": "PAS EMS Data Ops Tax Analyst",
    "source": "Unstop",
    "source_url": "https://unstop.com/undefined",
    "start_date": "2026-04-19T00:00:00+05:30",
    "end_date": "2026-05-03T00:00:00+05:30",
    "location": "",
    "college": ""
  },
  {
    "name": "PAS EMS Tax Analyst",
    "source": "Unstop",
    "source_url": "https://unstop.com/undefined",
    "start_date": "2026-04-19T00:00:00+05:30",
    "end_date": "2026-05-03T00:00:00+05:30",
    "location": "",
    "college": ""
  },
  {
    "name": "PAS Tax Analyst",
    "source": "Unstop",
    "source_url": "https://unstop.com/undefined",
    "start_date": "2026-04-19T00:00:00+05:30",
    "end_date": "2026-05-03T00:00:00+05:30",
    "location": "",
    "college": ""
  },
  {
    "name": "India Finance Team Analyst",
    "source": "Unstop",
    "source_url": "https://unstop.com/undefined",
    "start_date": "2026-04-18T00:00:00+05:30",
    "end_date": "2026-05-02T00:00:00+05:30",
    "location": "",
    "college": ""
  },
  {
    "name": "Evergreen Management Trainee",
    "source": "Unstop",
    "source_url": "https://unstop.com/undefined",
    "start_date": "2026-04-17T00:00:00+05:30",
    "end_date": "2026-05-01T00:00:00+05:30",
    "location": "",
    "college": ""
  },
  {
    "name": "mAD Libs",
    "source": "Unstop",
    "source_url": "https://unstop.com/undefined",
    "start_date": "2026-04-19T14:39:29+05:30",
    "end_date": "2026-04-23T16:00:29+05:30",
    "location": "",
    "college": ""
  },
  {
    "name": "Junior AI/ML Engineer",
    "source": "Unstop",
    "source_url": "https://unstop.com/undefined",
    "start_date": "2026-04-19T00:00:00+05:30",
    "end_date": "2026-05-03T00:00:00+05:30",
    "location": "",
    "college": ""
  },
  {
    "name": "Campus Marketing Internship",
    "source": "Unstop",
    "source_url": "https://unstop.com/undefined",
    "start_date": "2026-04-19T00:00:00+05:30",
    "end_date": "2026-05-03T00:00:00+05:30",
    "location": "",
    "college": ""
  },
  {
    "name": "Customer Support Executive – Chat Process",
    "source": "Unstop",
    "source_url": "https://unstop.com/undefined",
    "start_date": "2026-04-18T00:00:00+05:30",
    "end_date": "2026-05-02T00:00:00+05:30",
    "location": "",
    "college": ""
  },
  {
    "name": "PAS EMS-Switzerland-Tax Analyst",
    "source": "Unstop",
    "source_url": "https://unstop.com/undefined",
    "start_date": "2026-04-19T00:00:00+05:30",
    "end_date": "2026-05-03T00:00:00+05:30",
    "location": "",
    "college": ""
  },
  {
    "name": "PAS EMS-United Kingdom-Tax Analyst",
    "source": "Unstop",
    "source_url": "https://unstop.com/undefined",
    "start_date": "2026-04-19T00:00:00+05:30",
    "end_date": "2026-05-03T00:00:00+05:30",
    "location": "",
    "college": ""
  },
  {
    "name": "beyondstack - HackTheBrew",
    "source": "Unstop",
    "source_url": "https://unstop.com/undefined",
    "start_date": "2026-04-19T00:00:00+05:30",
    "end_date": "2026-05-01T00:00:00+05:30",
    "location": "",
    "college": ""
  },
  {
    "name": "Financial Analyst Internship",
    "source": "Unstop",
    "source_url": "https://unstop.com/undefined",
    "start_date": "2026-04-19T00:00:00+05:30",
    "end_date": "2026-05-03T00:00:00+05:30",
    "location": "",
    "college": ""
  },
  {
    "name": "Social Media & Community Management Internship",
    "source": "Unstop",
    "source_url": "https://unstop.com/undefined",
    "start_date": "2026-04-19T00:00:00+05:30",
    "end_date": "2026-05-03T00:00:00+05:30",
    "location": "",
    "college": ""
  },
  {
    "name": "Business Development Executive Internship",
    "source": "Unstop",
    "source_url": "https://unstop.com/undefined",
    "start_date": "2026-04-18T00:00:00+05:30",
    "end_date": "2026-04-30T05:42:00+05:30",
    "location": "",
    "college": ""
  },
  {
    "name": "Jr. UI / UX Designer Internship",
    "source": "Unstop",
    "source_url": "https://unstop.com/undefined",
    "start_date": "2026-04-19T00:00:00+05:30",
    "end_date": "2026-05-01T00:00:00+05:30",
    "location": "",
    "college": ""
  },
  {
    "name": "Jr. Web Developer Internship",
    "source": "Unstop",
    "source_url": "https://unstop.com/undefined",
    "start_date": "2026-04-19T00:00:00+05:30",
    "end_date": "2026-05-01T00:00:00+05:30",
    "location": "",
    "college": ""
  },
  {
    "name": "PAS IMT Service Activation - Data Operations - Tax Analyst",
    "source": "Unstop",
    "source_url": "https://unstop.com/undefined",
    "start_date": "2026-04-19T00:00:00+05:30",
    "end_date": "2026-05-03T00:00:00+05:30",
    "location": "",
    "college": ""
  },
  {
    "name": "Associate - Business Consultant (Mandarin Speaker)",
    "source": "Unstop",
    "source_url": "https://unstop.com/undefined",
    "start_date": "2026-04-18T00:00:00+05:30",
    "end_date": "2026-05-02T00:00:00+05:30",
    "location": "",
    "college": ""
  },
  {
    "name": "Sr Analyst - Chinese Language BSC",
    "source": "Unstop",
    "source_url": "https://unstop.com/undefined",
    "start_date": "2026-04-18T00:00:00+05:30",
    "end_date": "2026-05-02T00:00:00+05:30",
    "location": "",
    "college": ""
  },
  {
    "name": "ITTS - TP - Tax Core - Tax Analyst",
    "source": "Unstop",
    "source_url": "https://unstop.com/undefined",
    "start_date": "2026-04-18T00:00:00+05:30",
    "end_date": "2026-05-02T00:00:00+05:30",
    "location": "",
    "college": ""
  },
  {
    "name": "ITTS - TP - Data Operate - Tax Analyst",
    "source": "Unstop",
    "source_url": "https://unstop.com/undefined",
    "start_date": "2026-04-19T00:00:00+05:30",
    "end_date": "2026-05-03T00:00:00+05:30",
    "location": "",
    "college": ""
  },
  {
    "name": "Executive - GT Regulatory Capital Reporting",
    "source": "Unstop",
    "source_url": "https://unstop.com/undefined",
    "start_date": "2026-04-18T00:00:00+05:30",
    "end_date": "2026-05-02T00:00:00+05:30",
    "location": "",
    "college": ""
  },
  {
    "name": "PAS EMS - Tax Analyst (Netherlands)",
    "source": "Unstop",
    "source_url": "https://unstop.com/undefined",
    "start_date": "2026-04-19T00:00:00+05:30",
    "end_date": "2026-05-03T00:00:00+05:30",
    "location": "",
    "college": ""
  },
  {
    "name": "PAS EMS - Tax Analyst",
    "source": "Unstop",
    "source_url": "https://unstop.com/undefined",
    "start_date": "2026-04-19T00:00:00+05:30",
    "end_date": "2026-05-03T00:00:00+05:30",
    "location": "",
    "college": ""
  },
  {
    "name": "Administrator L2",
    "source": "Unstop",
    "source_url": "https://unstop.com/undefined",
    "start_date": "2026-04-19T00:00:00+05:30",
    "end_date": "2026-05-03T00:00:00+05:30",
    "location": "",
    "college": ""
  },
  {
    "name": "Technology Consulting Internship",
    "source": "Unstop",
    "source_url": "https://unstop.com/undefined",
    "start_date": "2026-04-19T00:00:00+05:30",
    "end_date": "2026-05-03T00:00:00+05:30",
    "location": "",
    "college": ""
  },
  {
    "name": "Business Development Executive - Gold Loan",
    "source": "Unstop",
    "source_url": "https://unstop.com/undefined",
    "start_date": "2026-04-19T00:00:00+05:30",
    "end_date": "2026-05-03T00:00:00+05:30",
    "location": "",
    "college": ""
  },
  {
    "name": "Developer L2",
    "source": "Unstop",
    "source_url": "https://unstop.com/undefined",
    "start_date": "2026-04-19T00:00:00+05:30",
    "end_date": "2026-05-03T00:00:00+05:30",
    "location": "",
    "college": ""
  },
  {
    "name": "Production Agent L1",
    "source": "Unstop",
    "source_url": "https://unstop.com/undefined",
    "start_date": "2026-04-19T00:00:00+05:30",
    "end_date": "2026-05-03T00:00:00+05:30",
    "location": "",
    "college": ""
  },
  {
    "name": "Business Development Executive (Lead Generation) Internship",
    "source": "Unstop",
    "source_url": "https://unstop.com/undefined",
    "start_date": "2026-04-19T14:44:39+05:30",
    "end_date": "2026-05-04T10:24:39+05:30",
    "location": "",
    "college": ""
  },
  {
    "name": "Data Engineer - Data Governance & Quality",
    "source": "Unstop",
    "source_url": "https://unstop.com/undefined",
    "start_date": "2026-04-19T00:00:00+05:30",
    "end_date": "2026-05-03T00:00:00+05:30",
    "location": "",
    "college": ""
  },
  {
    "name": "Telesales Internship",
    "source": "Unstop",
    "source_url": "https://unstop.com/undefined",
    "start_date": "2026-04-18T00:00:00+05:30",
    "end_date": "2026-05-02T00:00:00+05:30",
    "location": "",
    "college": ""
  },
  {
    "name": "Relationship Officer - Digital Banking",
    "source": "Unstop",
    "source_url": "https://unstop.com/undefined",
    "start_date": "2026-04-19T00:00:00+05:30",
    "end_date": "2026-05-03T00:00:00+05:30",
    "location": "",
    "college": ""
  },
  {
    "name": "Assistant Product Sales Manager",
    "source": "Unstop",
    "source_url": "https://unstop.com/undefined",
    "start_date": "2026-04-19T00:00:00+05:30",
    "end_date": "2026-05-03T00:00:00+05:30",
    "location": "",
    "college": ""
  },
  {
    "name": "The Climate Debate",
    "source": "Unstop",
    "source_url": "https://unstop.com/undefined",
    "start_date": "2026-04-19T00:00:00+05:30",
    "end_date": "2026-04-21T23:59:00+05:30",
    "location": "",
    "college": ""
  },
  {
    "name": "Feet on Fire",
    "source": "Unstop",
    "source_url": "https://unstop.com/undefined",
    "start_date": "2026-04-12T00:00:00+05:30",
    "end_date": "2026-04-25T21:00:00+05:30",
    "location": "",
    "college": ""
  },
  {
    "name": "Business Development Associate",
    "source": "Unstop",
    "source_url": "https://unstop.com/undefined",
    "start_date": "2026-04-19T00:00:00+05:30",
    "end_date": "2026-05-03T00:00:00+05:30",
    "location": "",
    "college": ""
  },
  {
    "name": "Valuation Validation",
    "source": "Unstop",
    "source_url": "https://unstop.com/undefined",
    "start_date": "2026-04-19T09:30:00+05:30",
    "end_date": "2026-04-21T16:00:00+05:30",
    "location": "",
    "college": ""
  },
  {
    "name": "UI / UX Designer Internship",
    "source": "Unstop",
    "source_url": "https://unstop.com/undefined",
    "start_date": "2026-04-19T00:00:00+05:30",
    "end_date": "2026-04-28T00:01:00+05:30",
    "location": "",
    "college": ""
  },
  {
    "name": "Student Mentor Internship",
    "source": "Unstop",
    "source_url": "https://unstop.com/undefined",
    "start_date": "2026-04-19T00:00:00+05:30",
    "end_date": "2026-04-22T23:58:00+05:30",
    "location": "",
    "college": ""
  },
  {
    "name": "नारी शक्ति: Dharma, Samman aur Vikas",
    "source": "Unstop",
    "source_url": "https://unstop.com/undefined",
    "start_date": "2026-04-19T00:00:00+05:30",
    "end_date": "2026-05-03T00:00:00+05:30",
    "location": "",
    "college": ""
  },
  {
    "name": "L’Affaires: The Trading Event",
    "source": "Unstop",
    "source_url": "https://unstop.com/undefined",
    "start_date": "2026-04-18T00:00:00+05:30",
    "end_date": "2026-04-22T19:00:00+05:30",
    "location": "",
    "college": ""
  },
  {
    "name": "Risk Consulting Associate",
    "source": "Unstop",
    "source_url": "https://unstop.com/undefined",
    "start_date": "2026-04-19T00:00:00+05:30",
    "end_date": "2026-05-03T00:00:00+05:30",
    "location": "",
    "college": ""
  },
  {
    "name": "Valuation Services Analyst",
    "source": "Unstop",
    "source_url": "https://unstop.com/undefined",
    "start_date": "2026-04-18T00:00:00+05:30",
    "end_date": "2026-05-02T00:00:00+05:30",
    "location": "",
    "college": ""
  },
  {
    "name": "Material Planning Analyst",
    "source": "Unstop",
    "source_url": "https://unstop.com/undefined",
    "start_date": "2026-04-18T00:00:00+05:30",
    "end_date": "2026-05-02T00:00:00+05:30",
    "location": "",
    "college": ""
  },
  {
    "name": "Associate Software Engineer",
    "source": "Unstop",
    "source_url": "https://unstop.com/undefined",
    "start_date": "2026-04-18T00:00:00+05:30",
    "end_date": "2026-05-02T00:00:00+05:30",
    "location": "",
    "college": ""
  },
  {
    "name": "Software Engineer",
    "source": "Unstop",
    "source_url": "https://unstop.com/undefined",
    "start_date": "2026-04-18T00:00:00+05:30",
    "end_date": "2026-05-02T00:00:00+05:30",
    "location": "",
    "college": ""
  },
  {
    "name": "First Line Risk Management Analyst",
    "source": "Unstop",
    "source_url": "https://unstop.com/undefined",
    "start_date": "2026-04-18T00:00:00+05:30",
    "end_date": "2026-05-02T00:00:00+05:30",
    "location": "",
    "college": ""
  },
  {
    "name": "Subject Matter Expert - Issuer Services",
    "source": "Unstop",
    "source_url": "https://unstop.com/undefined",
    "start_date": "2026-04-18T00:00:00+05:30",
    "end_date": "2026-05-02T00:00:00+05:30",
    "location": "",
    "college": ""
  },
  {
    "name": "Relationship Management Trainee",
    "source": "Unstop",
    "source_url": "https://unstop.com/undefined",
    "start_date": "2026-04-18T00:00:00+05:30",
    "end_date": "2026-05-02T00:00:00+05:30",
    "location": "",
    "college": ""
  },
  {
    "name": "Principal Architect",
    "source": "Unstop",
    "source_url": "https://unstop.com/undefined",
    "start_date": "2026-04-18T00:00:00+05:30",
    "end_date": "2026-05-02T00:00:00+05:30",
    "location": "",
    "college": ""
  },
  {
    "name": "Cloud Architect",
    "source": "Unstop",
    "source_url": "https://unstop.com/undefined",
    "start_date": "2026-04-18T00:00:00+05:30",
    "end_date": "2026-05-02T00:00:00+05:30",
    "location": "",
    "college": ""
  },
  {
    "name": "Global AI Atlas: Guinness World Records™ Attempt - Global Contributor Campaign",
    "source": "Unstop",
    "source_url": "https://unstop.com/undefined",
    "start_date": "2026-04-18T00:00:00+05:30",
    "end_date": "2026-05-18T00:00:00+05:30",
    "location": "",
    "college": ""
  },
  {
    "name": "Mantavya 26",
    "source": "Unstop",
    "source_url": "https://unstop.com/undefined",
    "start_date": "2026-04-18T00:00:00+05:30",
    "end_date": "2026-05-02T00:00:00+05:30",
    "location": "",
    "college": ""
  },
  {
    "name": "Compensation Platform Support Analyst",
    "source": "Unstop",
    "source_url": "https://unstop.com/undefined",
    "start_date": "2026-04-18T00:00:00+05:30",
    "end_date": "2026-05-02T00:00:00+05:30",
    "location": "",
    "college": ""
  },
  {
    "name": "Business Analyst",
    "source": "Unstop",
    "source_url": "https://unstop.com/undefined",
    "start_date": "2026-04-18T00:00:00+05:30",
    "end_date": "2026-05-02T00:00:00+05:30",
    "location": "",
    "college": ""
  },
  {
    "name": "GenAI Developer",
    "source": "Unstop",
    "source_url": "https://unstop.com/undefined",
    "start_date": "2026-04-18T00:00:00+05:30",
    "end_date": "2026-05-02T00:00:00+05:30",
    "location": "",
    "college": ""
  },
  {
    "name": "Data Scientist",
    "source": "Unstop",
    "source_url": "https://unstop.com/undefined",
    "start_date": "2026-04-18T00:00:00+05:30",
    "end_date": "2026-05-02T00:00:00+05:30",
    "location": "",
    "college": ""
  },
  {
    "name": "AP Invoice Processing Process Expert",
    "source": "Unstop",
    "source_url": "https://unstop.com/undefined",
    "start_date": "2026-04-18T00:00:00+05:30",
    "end_date": "2026-05-02T00:00:00+05:30",
    "location": "",
    "college": ""
  },
  {
    "name": "Cloud Platform Engineer",
    "source": "Unstop",
    "source_url": "https://unstop.com/undefined",
    "start_date": "2026-04-18T00:00:00+05:30",
    "end_date": "2026-05-02T00:00:00+05:30",
    "location": "",
    "college": ""
  },
  {
    "name": "Senior Engineer",
    "source": "Unstop",
    "source_url": "https://unstop.com/undefined",
    "start_date": "2026-04-18T00:00:00+05:30",
    "end_date": "2026-05-02T00:00:00+05:30",
    "location": "",
    "college": ""
  },
  {
    "name": "Legal Assistant Manager",
    "source": "Unstop",
    "source_url": "https://unstop.com/undefined",
    "start_date": "2026-04-18T00:00:00+05:30",
    "end_date": "2026-05-02T00:00:00+05:30",
    "location": "",
    "college": ""
  },
  {
    "name": "The Math-O-Logic Challenge!",
    "source": "Unstop",
    "source_url": "https://unstop.com/undefined",
    "start_date": "2026-04-18T00:00:00+05:30",
    "end_date": "2026-05-05T23:59:00+05:30",
    "location": "",
    "college": ""
  },
  {
    "name": "Equithon - The Equity Research Competition",
    "source": "Unstop",
    "source_url": "https://unstop.com/undefined",
    "start_date": "2026-04-14T00:00:00+05:30",
    "end_date": "2026-04-23T23:59:00+05:30",
    "location": "",
    "college": ""
  },
  {
    "name": "Campus Ambassador Internship",
    "source": "Unstop",
    "source_url": "https://unstop.com/undefined",
    "start_date": "2026-04-18T00:00:00+05:30",
    "end_date": "2026-05-02T00:00:00+05:30",
    "location": "",
    "college": ""
  },
  {
    "name": "Business Development Internship",
    "source": "Unstop",
    "source_url": "https://unstop.com/undefined",
    "start_date": "2026-04-18T00:00:00+05:30",
    "end_date": "2026-05-02T00:00:00+05:30",
    "location": "",
    "college": ""
  },
  {
    "name": "Pre Sales Executive",
    "source": "Unstop",
    "source_url": "https://unstop.com/undefined",
    "start_date": "2026-04-18T00:00:00+05:30",
    "end_date": "2026-04-25T23:57:00+05:30",
    "location": "",
    "college": ""
  },
  {
    "name": "Business Development Executive (BDE)",
    "source": "Unstop",
    "source_url": "https://unstop.com/undefined",
    "start_date": "2026-04-17T00:00:00+05:30",
    "end_date": "2026-05-01T00:00:00+05:30",
    "location": "",
    "college": ""
  },
  {
    "name": "Red Dot Chronicles 2.0",
    "source": "Unstop",
    "source_url": "https://unstop.com/undefined",
    "start_date": "2026-04-17T17:00:00+05:30",
    "end_date": "2026-04-24T10:31:00+05:30",
    "location": "",
    "college": ""
  },
  {
    "name": "Content Creation / Writing Internship",
    "source": "Unstop",
    "source_url": "https://unstop.com/undefined",
    "start_date": "2026-04-18T00:00:00+05:30",
    "end_date": "2026-05-02T00:00:00+05:30",
    "location": "",
    "college": ""
  },
  {
    "name": "Retail Store Manager",
    "source": "Unstop",
    "source_url": "https://unstop.com/undefined",
    "start_date": "2026-04-18T00:00:00+05:30",
    "end_date": "2026-05-02T00:00:00+05:30",
    "location": "",
    "college": ""
  },
  {
    "name": "GeM Portal Manager",
    "source": "Unstop",
    "source_url": "https://unstop.com/undefined",
    "start_date": "2026-04-18T00:00:00+05:30",
    "end_date": "2026-05-02T00:00:00+05:30",
    "location": "",
    "college": ""
  },
  {
    "name": "Campus Ambassador",
    "source": "Unstop",
    "source_url": "https://unstop.com/undefined",
    "start_date": "2026-04-19T00:00:18+05:30",
    "end_date": "2026-04-25T23:53:18+05:30",
    "location": "",
    "college": ""
  },
  {
    "name": "Recruitment Marketing & Branding Internship",
    "source": "Unstop",
    "source_url": "https://unstop.com/undefined",
    "start_date": "2026-04-18T00:00:00+05:30",
    "end_date": "2026-05-02T00:00:00+05:30",
    "location": "",
    "college": ""
  },
  {
    "name": "Social Debate Competition",
    "source": "Unstop",
    "source_url": "https://unstop.com/undefined",
    "start_date": "2026-04-18T00:00:00+05:30",
    "end_date": "2026-04-22T18:00:00+05:30",
    "location": "",
    "college": ""
  },
  {
    "name": "Capital Conquest 3.0",
    "source": "Unstop",
    "source_url": "https://unstop.com/undefined",
    "start_date": "2026-04-18T00:00:00+05:30",
    "end_date": "2026-04-23T16:00:00+05:30",
    "location": "",
    "college": ""
  },
  {
    "name": "Video Editor & Graphic Designer Internship",
    "source": "Unstop",
    "source_url": "https://unstop.com/undefined",
    "start_date": "2026-04-18T00:00:00+05:30",
    "end_date": "2026-05-02T00:00:00+05:30",
    "location": "",
    "college": ""
  },
  {
    "name": "Quality Engineer",
    "source": "Unstop",
    "source_url": "https://unstop.com/undefined",
    "start_date": "2026-04-18T00:00:00+05:30",
    "end_date": "2026-05-02T00:00:00+05:30",
    "location": "",
    "college": ""
  },
  {
    "name": "Web Developer Internship",
    "source": "Unstop",
    "source_url": "https://unstop.com/undefined",
    "start_date": "2026-04-18T00:00:00+05:30",
    "end_date": "2026-05-02T00:00:00+05:30",
    "location": "",
    "college": ""
  },
  {
    "name": "India's Biggest Creators' League",
    "source": "Unstop",
    "source_url": "https://unstop.com/undefined",
    "start_date": "2026-04-16T00:00:00+05:30",
    "end_date": "2026-05-10T23:59:17+05:30",
    "location": "",
    "college": ""
  },
  {
    "name": "Social Media Marketing Internship",
    "source": "Unstop",
    "source_url": "https://unstop.com/undefined",
    "start_date": "2026-04-18T00:00:00+05:30",
    "end_date": "2026-05-02T00:00:00+05:30",
    "location": "",
    "college": ""
  },
  {
    "name": "Admissions Internship",
    "source": "Unstop",
    "source_url": "https://unstop.com/undefined",
    "start_date": "2026-04-18T00:00:00+05:30",
    "end_date": "2026-04-21T23:58:00+05:30",
    "location": "",
    "college": ""
  },
  {
    "name": "Sales and Marketing Internship",
    "source": "Unstop",
    "source_url": "https://unstop.com/undefined",
    "start_date": "2026-04-18T00:00:00+05:30",
    "end_date": "2026-05-02T00:00:00+05:30",
    "location": "",
    "college": ""
  },
  {
    "name": "Think Or Sink",
    "source": "Unstop",
    "source_url": "https://unstop.com/undefined",
    "start_date": "2026-04-18T00:00:00+05:30",
    "end_date": "2026-04-25T21:00:00+05:30",
    "location": "",
    "college": ""
  },
  {
    "name": "Senior Sales Executive",
    "source": "Unstop",
    "source_url": "https://unstop.com/undefined",
    "start_date": "2026-04-18T00:00:00+05:30",
    "end_date": "2026-05-02T00:00:00+05:30",
    "location": "",
    "college": ""
  },
  {
    "name": "Pixel Play",
    "source": "Unstop",
    "source_url": "https://unstop.com/undefined",
    "start_date": "2026-04-18T22:00:00+05:30",
    "end_date": "2026-05-07T23:01:00+05:30",
    "location": "",
    "college": ""
  },
  {
    "name": "Business Development Executive",
    "source": "Unstop",
    "source_url": "https://unstop.com/undefined",
    "start_date": "2026-04-18T00:00:00+05:30",
    "end_date": "2026-05-02T00:00:00+05:30",
    "location": "",
    "college": ""
  },
  {
    "name": "SW Development Engineer 1 - Android",
    "source": "Unstop",
    "source_url": "https://unstop.com/undefined",
    "start_date": "2026-04-17T00:00:00+05:30",
    "end_date": "2026-05-01T00:00:00+05:30",
    "location": "",
    "college": ""
  },
  {
    "name": "Investment Banking Internship",
    "source": "Unstop",
    "source_url": "https://unstop.com/undefined",
    "start_date": "2026-04-18T00:00:00+05:30",
    "end_date": "2026-05-02T00:00:00+05:30",
    "location": "",
    "college": ""
  },
  {
    "name": "Service Desk Analyst",
    "source": "Unstop",
    "source_url": "https://unstop.com/undefined",
    "start_date": "2026-04-18T00:00:00+05:30",
    "end_date": "2026-05-02T00:00:00+05:30",
    "location": "",
    "college": ""
  },
  {
    "name": "Account Manager I",
    "source": "Unstop",
    "source_url": "https://unstop.com/undefined",
    "start_date": "2026-04-17T00:00:00+05:30",
    "end_date": "2026-05-01T00:00:00+05:30",
    "location": "",
    "college": ""
  },
  {
    "name": "Sales Internship",
    "source": "Unstop",
    "source_url": "https://unstop.com/undefined",
    "start_date": "2026-04-18T00:00:00+05:30",
    "end_date": "2026-05-02T00:00:00+05:30",
    "location": "",
    "college": ""
  },
  {
    "name": "Tally Accountant",
    "source": "Unstop",
    "source_url": "https://unstop.com/undefined",
    "start_date": "2026-04-18T00:00:00+05:30",
    "end_date": "2026-05-02T00:00:00+05:30",
    "location": "",
    "college": ""
  },
  {
    "name": "Civil Engineer",
    "source": "Unstop",
    "source_url": "https://unstop.com/undefined",
    "start_date": "2026-04-18T00:00:00+05:30",
    "end_date": "2026-04-25T00:00:00+05:30",
    "location": "",
    "college": ""
  },
  {
    "name": "Data Science Internship",
    "source": "Unstop",
    "source_url": "https://unstop.com/undefined",
    "start_date": "2026-04-18T00:00:00+05:30",
    "end_date": "2026-05-02T00:00:00+05:30",
    "location": "",
    "college": ""
  },
  {
    "name": "Process Design Engineer",
    "source": "Unstop",
    "source_url": "https://unstop.com/undefined",
    "start_date": "2026-04-18T00:00:00+05:30",
    "end_date": "2026-05-02T00:00:00+05:30",
    "location": "",
    "college": ""
  },
  {
    "name": "Call for Research Articles & Papers: NITI 2026",
    "source": "Unstop",
    "source_url": "https://unstop.com/undefined",
    "start_date": "2026-04-14T00:00:00+05:30",
    "end_date": "2026-05-05T23:59:00+05:30",
    "location": "",
    "college": ""
  },
  {
    "name": "Technology Research & Innovation Engineer",
    "source": "Unstop",
    "source_url": "https://unstop.com/undefined",
    "start_date": "2026-04-18T00:00:00+05:30",
    "end_date": "2026-05-02T00:00:00+05:30",
    "location": "",
    "college": ""
  },
  {
    "name": "Campus Representative",
    "source": "Unstop",
    "source_url": "https://unstop.com/undefined",
    "start_date": "2026-04-18T00:00:00+05:30",
    "end_date": "2026-05-02T00:00:00+05:30",
    "location": "",
    "college": ""
  },
  {
    "name": "Dhurandhar CTF",
    "source": "Unstop",
    "source_url": "https://unstop.com/undefined",
    "start_date": "2026-04-16T01:00:00+05:30",
    "end_date": "2026-04-26T00:00:00+05:30",
    "location": "",
    "college": ""
  },
  {
    "name": "Content Creation Internship",
    "source": "Unstop",
    "source_url": "https://unstop.com/undefined",
    "start_date": "2026-04-18T00:00:00+05:30",
    "end_date": "2026-05-02T00:00:00+05:30",
    "location": "",
    "college": ""
  },
  {
    "name": "Feild Sales Executive",
    "source": "Unstop",
    "source_url": "https://unstop.com/undefined",
    "start_date": "2026-04-18T00:00:00+05:30",
    "end_date": "2026-05-02T00:00:00+05:30",
    "location": "",
    "college": ""
  },
  {
    "name": "Python Developer Internship",
    "source": "Unstop",
    "source_url": "https://unstop.com/undefined",
    "start_date": "2026-04-18T14:39:10+05:30",
    "end_date": "2026-05-03T14:39:10+05:30",
    "location": "",
    "college": ""
  },
  {
    "name": "Sales Officer",
    "source": "Unstop",
    "source_url": "https://unstop.com/undefined",
    "start_date": "2026-04-18T00:00:00+05:30",
    "end_date": "2026-05-02T00:00:00+05:30",
    "location": "",
    "college": ""
  },
  {
    "name": "Pitch Your Brand VC Edition - E-Summit'26",
    "source": "Unstop",
    "source_url": "https://unstop.com/undefined",
    "start_date": "2026-04-19T00:00:00+05:30",
    "end_date": "2026-04-29T14:59:00+05:30",
    "location": "",
    "college": ""
  },
  {
    "name": "Full Stack Developer",
    "source": "Unstop",
    "source_url": "https://unstop.com/undefined",
    "start_date": "2026-04-18T00:00:00+05:30",
    "end_date": "2026-05-02T00:00:00+05:30",
    "location": "",
    "college": ""
  },
  {
    "name": "Interior Designer",
    "source": "Unstop",
    "source_url": "https://unstop.com/undefined",
    "start_date": "2026-04-18T00:00:00+05:30",
    "end_date": "2026-05-02T00:00:00+05:30",
    "location": "",
    "college": ""
  },
  {
    "name": "Business Development Manager",
    "source": "Unstop",
    "source_url": "https://unstop.com/undefined",
    "start_date": "2026-04-13T00:00:00+05:30",
    "end_date": "2026-04-27T00:00:00+05:30",
    "location": "",
    "college": ""
  },
  {
    "name": "Ex-Machina",
    "source": "Unstop",
    "source_url": "https://unstop.com/undefined",
    "start_date": "2026-04-18T00:00:00+05:30",
    "end_date": "2026-04-19T18:00:00+05:30",
    "location": "",
    "college": ""
  },
  {
    "name": "Marketing & Sales Internship",
    "source": "Unstop",
    "source_url": "https://unstop.com/undefined",
    "start_date": "2026-04-18T00:00:00+05:30",
    "end_date": "2026-05-02T00:00:00+05:30",
    "location": "",
    "college": ""
  },
  {
    "name": "Inside Sales Executive",
    "source": "Unstop",
    "source_url": "https://unstop.com/undefined",
    "start_date": "2026-04-18T00:00:00+05:30",
    "end_date": "2026-05-01T00:00:00+05:30",
    "location": "",
    "college": ""
  },
  {
    "name": "Software Development Engineer Intern",
    "source": "Unstop",
    "source_url": "https://unstop.com/undefined",
    "start_date": "2026-04-18T00:00:00+05:30",
    "end_date": "2026-05-02T00:00:00+05:30",
    "location": "",
    "college": ""
  },
  {
    "name": "Content Marketing Internship",
    "source": "Unstop",
    "source_url": "https://unstop.com/undefined",
    "start_date": "2026-04-18T00:00:00+05:30",
    "end_date": "2026-05-02T00:00:00+05:30",
    "location": "",
    "college": ""
  },
  {
    "name": "Inside Sales Associate",
    "source": "Unstop",
    "source_url": "https://unstop.com/undefined",
    "start_date": "2026-04-18T00:00:00+05:30",
    "end_date": "2026-05-02T00:00:00+05:30",
    "location": "",
    "college": ""
  },
  {
    "name": "Junior Accountant",
    "source": "Unstop",
    "source_url": "https://unstop.com/undefined",
    "start_date": "2026-04-18T00:00:00+05:30",
    "end_date": "2026-05-02T00:00:00+05:30",
    "location": "",
    "college": ""
  },
  {
    "name": "Student Coordinator Internship",
    "source": "Unstop",
    "source_url": "https://unstop.com/undefined",
    "start_date": "2026-04-18T00:00:00+05:30",
    "end_date": "2026-05-02T00:00:00+05:30",
    "location": "",
    "college": ""
  },
  {
    "name": "Customer Service Representative",
    "source": "Unstop",
    "source_url": "https://unstop.com/undefined",
    "start_date": "2026-04-18T00:00:00+05:30",
    "end_date": "2026-05-02T00:00:00+05:30",
    "location": "",
    "college": ""
  },
  {
    "name": "Join a Free AI-Powered Testing Demo by Quality Thought",
    "source": "Unstop",
    "source_url": "https://unstop.com/undefined",
    "start_date": "2026-04-18T00:00:00+05:30",
    "end_date": "2026-04-23T09:30:00+05:30",
    "location": "",
    "college": ""
  },
  {
    "name": "Accounts Executive",
    "source": "Unstop",
    "source_url": "https://unstop.com/undefined",
    "start_date": "2026-04-18T00:00:00+05:30",
    "end_date": "2026-05-02T00:00:00+05:30",
    "location": "",
    "college": ""
  },
  {
    "name": "Showroom Sales Executive",
    "source": "Unstop",
    "source_url": "https://unstop.com/undefined",
    "start_date": "2026-04-18T00:00:00+05:30",
    "end_date": "2026-05-02T00:00:00+05:30",
    "location": "",
    "college": ""
  },
  {
    "name": "Online Workshop on Canva: Design, Content Creation & Visual Communication",
    "source": "Unstop",
    "source_url": "https://unstop.com/undefined",
    "start_date": "2026-04-18T00:00:00+05:30",
    "end_date": "2026-04-20T15:01:00+05:30",
    "location": "",
    "college": ""
  },
  {
    "name": "Accounts Receivable Executive",
    "source": "Unstop",
    "source_url": "https://unstop.com/undefined",
    "start_date": "2026-04-17T00:00:00+05:30",
    "end_date": "2026-05-01T00:00:00+05:30",
    "location": "",
    "college": ""
  },
  {
    "name": "Enterprise Sales Manager",
    "source": "Unstop",
    "source_url": "https://unstop.com/undefined",
    "start_date": "2026-04-17T00:00:00+05:30",
    "end_date": "2026-05-01T00:00:00+05:30",
    "location": "",
    "college": ""
  },
  {
    "name": "Field Sales Executive",
    "source": "Unstop",
    "source_url": "https://unstop.com/undefined",
    "start_date": "2026-04-17T00:00:00+05:30",
    "end_date": "2026-05-01T00:00:00+05:30",
    "location": "",
    "college": ""
  },
  {
    "name": "HR Service Delivery New Associate",
    "source": "Unstop",
    "source_url": "https://unstop.com/undefined",
    "start_date": "2026-04-17T00:00:00+05:30",
    "end_date": "2026-05-01T00:00:00+05:30",
    "location": "",
    "college": ""
  },
  {
    "name": "Digital Manufacturing & IoT Lead",
    "source": "Unstop",
    "source_url": "https://unstop.com/undefined",
    "start_date": "2026-04-18T00:00:00+05:30",
    "end_date": "2026-05-02T00:00:00+05:30",
    "location": "",
    "college": ""
  },
  {
    "name": "Sales & Royalty Audit Analyst",
    "source": "Unstop",
    "source_url": "https://unstop.com/undefined",
    "start_date": "2026-04-18T00:00:00+05:30",
    "end_date": "2026-05-02T00:00:00+05:30",
    "location": "",
    "college": ""
  },
  {
    "name": "Retail Sales Officer",
    "source": "Unstop",
    "source_url": "https://unstop.com/undefined",
    "start_date": "2026-04-18T00:00:00+05:30",
    "end_date": "2026-05-02T00:00:00+05:30",
    "location": "",
    "college": ""
  },
  {
    "name": "Marketing and Lead Development Internship",
    "source": "Unstop",
    "source_url": "https://unstop.com/undefined",
    "start_date": "2026-04-18T00:00:00+05:30",
    "end_date": "2026-05-02T00:00:00+05:30",
    "location": "",
    "college": ""
  },
  {
    "name": "E-Commerce Executive",
    "source": "Unstop",
    "source_url": "https://unstop.com/undefined",
    "start_date": "2026-04-18T00:00:00+05:30",
    "end_date": "2026-05-02T00:00:00+05:30",
    "location": "",
    "college": ""
  },
  {
    "name": "Accounts Manager",
    "source": "Unstop",
    "source_url": "https://unstop.com/undefined",
    "start_date": "2026-04-18T00:00:00+05:30",
    "end_date": "2026-05-02T00:00:00+05:30",
    "location": "",
    "college": ""
  },
  {
    "name": "Customer Service Executive",
    "source": "Unstop",
    "source_url": "https://unstop.com/undefined",
    "start_date": "2026-04-10T00:00:00+05:30",
    "end_date": "2026-04-24T00:00:00+05:30",
    "location": "",
    "college": ""
  },
  {
    "name": "Tele Callers Associate",
    "source": "Unstop",
    "source_url": "https://unstop.com/undefined",
    "start_date": "2026-04-18T00:00:00+05:30",
    "end_date": "2026-05-02T00:00:00+05:30",
    "location": "",
    "college": ""
  },
  {
    "name": "Marketing & HR Internship",
    "source": "Unstop",
    "source_url": "https://unstop.com/undefined",
    "start_date": "2026-04-18T00:00:00+05:30",
    "end_date": "2026-05-02T00:00:00+05:30",
    "location": "",
    "college": ""
  },
  {
    "name": "AI Intern – Image Intelligence & Automation",
    "source": "Unstop",
    "source_url": "https://unstop.com/undefined",
    "start_date": "2026-04-18T00:00:00+05:30",
    "end_date": "2026-05-02T00:00:00+05:30",
    "location": "",
    "college": ""
  },
  {
    "name": "Global Travel Optimization Challenge",
    "source": "Unstop",
    "source_url": "https://unstop.com/undefined",
    "start_date": "2026-04-18T00:00:00+05:30",
    "end_date": "2026-05-03T10:56:00+05:30",
    "location": "",
    "college": ""
  },
  {
    "name": "SQL Workshop - TVASTR 26’",
    "source": "Unstop",
    "source_url": "https://unstop.com/undefined",
    "start_date": "2026-04-18T00:00:00+05:30",
    "end_date": "2026-04-25T12:01:00+05:30",
    "location": "",
    "college": ""
  },
  {
    "name": "Interior Design Internship",
    "source": "Unstop",
    "source_url": "https://unstop.com/undefined",
    "start_date": "2026-04-18T00:00:00+05:30",
    "end_date": "2026-05-02T00:05:00+05:30",
    "location": "",
    "college": ""
  },
  {
    "name": "Web Marketing Executive",
    "source": "Unstop",
    "source_url": "https://unstop.com/undefined",
    "start_date": "2026-04-17T00:00:00+05:30",
    "end_date": "2026-05-01T00:00:00+05:30",
    "location": "",
    "college": ""
  },
  {
    "name": "Maintenance Mechanical Engineer",
    "source": "Unstop",
    "source_url": "https://unstop.com/undefined",
    "start_date": "2026-04-18T00:00:00+05:30",
    "end_date": "2026-05-02T00:00:00+05:30",
    "location": "",
    "college": ""
  },
  {
    "name": "Decode & Display – Data Visualization Challenge",
    "source": "Unstop",
    "source_url": "https://unstop.com/undefined",
    "start_date": "2026-04-18T00:00:00+05:30",
    "end_date": "2026-04-25T17:00:00+05:30",
    "location": "",
    "college": ""
  },
  {
    "name": "Umang",
    "source": "Unstop",
    "source_url": "https://unstop.com/undefined",
    "start_date": "2026-04-18T00:00:00+05:30",
    "end_date": "2026-04-21T12:00:00+05:30",
    "location": "",
    "college": ""
  }
]